lib_eic/__init__.py
lib_eic/__main__.py
lib_eic/cli.py
lib_eic/config.py
lib_eic/logging_setup.py
lib_eic/parallel.py
lib_eic/processor.py
lib_eic/progress.py
lib_eic/validation.py
lib_eic/analysis/__init__.py
lib_eic/analysis/eic.py
lib_eic/analysis/fitting.py
lib_eic/analysis/ms2.py
lib_eic/chemistry/__init__.py
lib_eic/chemistry/adducts.py
lib_eic/chemistry/mass.py
lib_eic/io/__init__.py
lib_eic/io/excel.py
lib_eic/io/plotting.py
lib_eic/io/raw_file.py
lib_eic-0.2.2.dist-info/entry_points.txt
lib_eic-0.2.2.dist-info/licenses/LICENSE
lib_eic-0.2.2.dist-info/WHEEL
lib_eic-0.2.2.dist-info/METADATA
lib_eic-0.2.2.dist-info/RECORD
