Metadata-Version: 2.4
Name: lib_eic
Version: 0.2.2
Summary: Automated Targeted Feature Extraction & Adduct Verification Tool for LC-MS Data.
Keywords: lcms,mass-spectrometry,metabolomics,adduct,chromatography
Author-email: Jihyun Chun <jihyun5311@snu.ac.kr>, Daehwan Kim <kdh5358@snu.ac.kr>
Requires-Python: >=3.8
Classifier: Programming Language :: Python :: 3
Classifier: Programming Language :: Python :: 3.8
Classifier: Programming Language :: Python :: 3.9
Classifier: Programming Language :: Python :: 3.10
Classifier: Programming Language :: Python :: 3.11
Classifier: Programming Language :: Python :: 3.12
Classifier: License :: OSI Approved :: MIT License
Classifier: Operating System :: OS Independent
Classifier: Intended Audience :: Science/Research
Classifier: Topic :: Scientific/Engineering :: Chemistry
License-File: LICENSE
Requires-Dist: pandas>=2.0.0,<3.0
Requires-Dist: openpyxl>=3.1.0,<4.0
Requires-Dist: molmass>=2022.0.0
Requires-Dist: scipy>=1.10.0,<2.0
Requires-Dist: matplotlib>=3.7.0,<4.0
Requires-Dist: numpy>=1.24.0,<2.0
Requires-Dist: fisher-py>=1.0.0
Requires-Dist: pythonnet>=3.0.0
Requires-Dist: tqdm>=4.66.0,<5.0
Requires-Dist: pyyaml>=6.0 ; extra == "all"
Requires-Dist: pytest>=7.0 ; extra == "dev"
Requires-Dist: pytest-cov>=4.0 ; extra == "dev"
Requires-Dist: black>=24.0 ; extra == "dev"
Requires-Dist: ruff>=0.1.0 ; extra == "dev"
Requires-Dist: pyrefly>=0.46.0 ; extra == "dev"
Requires-Dist: pyyaml>=6.0 ; extra == "dev"
Requires-Dist: pyyaml>=6.0 ; extra == "yaml"
Project-URL: Homepage, https://github.com/SNUFML/lib_eic
Project-URL: Issues, https://github.com/SNUFML/lib_eic/issues
Project-URL: Repository, https://github.com/SNUFML/lib_eic
Provides-Extra: all
Provides-Extra: dev
Provides-Extra: yaml
